pykerr/__init__.py
pykerr/_version.py
pykerr/harmonics.py
pykerr/qnm.py
pykerr/data/l2.hdf
pykerr/data/l3.hdf
pykerr/data/l4.hdf
pykerr/data/l5.hdf
pykerr/data/l6.hdf
pykerr/data/l7.hdf
pykerr-0.1.0.dist-info/LICENSE
pykerr-0.1.0.dist-info/METADATA
pykerr-0.1.0.dist-info/WHEEL
pykerr-0.1.0.dist-info/top_level.txt
pykerr-0.1.0.dist-info/RECORD
