Metadata-Version: 2.1
Name: pykerr
Version: 0.1.0
Summary: QNM frequencies and spheroidal harmonics of Kerr black holes.
Home-page: https://github.com/cdcapano/pykerr.git
Author: Collin Capano
Author-email: collin.capano@aei.mpg.de
License: UNKNOWN
Platform: UNKNOWN
Classifier: Programming Language :: Python :: 2.7
Classifier: Programming Language :: Python :: 3
Classifier: License :: OSI Approved :: GNU General Public License v3 (GPLv3)
Classifier: Operating System :: OS Independent
Classifier: Intended Audience :: Science/Research
Classifier: Natural Language :: English
